gcphcp/__init__.py
gcphcp/constants.py
gcphcp/auth/__init__.py
gcphcp/auth/exceptions.py
gcphcp/auth/google_auth.py
gcphcp/cli/__init__.py
gcphcp/cli/main.py
gcphcp/cli/commands/__init__.py
gcphcp/cli/commands/auth.py
gcphcp/cli/commands/clusters.py
gcphcp/cli/commands/config.py
gcphcp/cli/commands/infra.py
gcphcp/cli/commands/nodepools.py
gcphcp/client/__init__.py
gcphcp/client/api_client.py
gcphcp/client/exceptions.py
gcphcp/models/__init__.py
gcphcp/models/cluster.py
gcphcp/models/nodepool.py
gcphcp/utils/__init__.py
gcphcp/utils/config.py
gcphcp/utils/crypto.py
gcphcp/utils/formatters.py
gcphcp/utils/hypershift.py
gcphcp/utils/kubeconfig.py
gcphcp-1.0.0.dist-info/METADATA
gcphcp-1.0.0.dist-info/WHEEL
gcphcp-1.0.0.dist-info/entry_points.txt
gcphcp-1.0.0.dist-info/licenses/LICENSE
gcphcp-1.0.0.dist-info/RECORD
